pynpress/__init__.py
pynpress/launcher.py
pynpress/py.typed
pynpress/wallets/__init__.py
pynpress/wallets/base.py
pynpress/wallets/metamask/__init__.py
pynpress/wallets/metamask/core.py
pynpress/wallets/metamask/locators.py
pynpress-0.1.0.dist-info/WHEEL
pynpress-0.1.0.dist-info/METADATA
pynpress-0.1.0.dist-info/RECORD
