Metadata-Version: 2.3
Name: pynpress
Version: 0.1.0
Summary: Add your description here
Author: lanyi
Author-email: lanyi <31091395+lanyi1998@users.noreply.github.com>
Requires-Dist: playwright>=1.57.0
Requires-Dist: pytest-playwright>=0.7.2
Requires-Python: >=3.10
